epl/__init__.py
epl/cluster.py
epl/config.py
epl/env.py
epl/communicators/__init__.py
epl/communicators/base.py
epl/communicators/collective_communicator.py
epl/communicators/collective_keys.py
epl/communicators/communication_pool.py
epl/communicators/libcommunicators.so
epl/communicators/nccl.py
epl/communicators/nccl_ops.py
epl/communicators/options.py
epl/communicators/pywrap.py
epl/communicators/rewriters/__init__.py
epl/communicators/rewriters/base.py
epl/communicators/rewriters/coalescing.py
epl/communicators/rewriters/sparse_allreduce.py
epl/ir/__init__.py
epl/ir/function.py
epl/ir/graph.py
epl/ir/layer.py
epl/ir/op_cluster.py
epl/ir/operation.py
epl/ir/phase.py
epl/ir/shape.py
epl/ir/sharding_base.py
epl/ir/taskgraph.py
epl/ir/tensor.py
epl/ir/variable.py
epl/ops/__init__.py
epl/ops/adam_weight_decay_optimizer.py
epl/ops/bridging_layer.py
epl/ops/distributed_dense.py
epl/ops/distributed_losses.py
epl/ops/distributed_ops.py
epl/ops/initializers.py
epl/parallel/__init__.py
epl/parallel/graph_editor.py
epl/parallel/hooks.py
epl/parallel/ops.py
epl/parallel/parallel.py
epl/parallel/partitioner.py
epl/parallel/planner.py
epl/profiler/__init__.py
epl/profiler/flops.py
epl/profiler/memory_profiler_hook.py
epl/profiler/profiler.py
epl/runtime/__init__.py
epl/runtime/gradient_accumulation.py
epl/runtime/optimizer_helper.py
epl/runtime/saver.py
epl/runtime/zero.py
epl/runtime/amp/__init__.py
epl/runtime/amp/auto_mixed_precision.py
epl/runtime/amp/loss_scale.py
epl/runtime/amp/loss_scale_tf.py
epl/runtime/gc/__init__.py
epl/runtime/gc/auto_gradient_checkpoint.py
epl/runtime/gc/gradient_checkpoint.py
epl/strategies/__init__.py
epl/strategies/parallel_strategy.py
epl/strategies/replicate.py
epl/strategies/scheduler.py
epl/strategies/split.py
epl/strategies/strategy_context.py
epl/utils/__init__.py
epl/utils/common.py
epl/utils/constant.py
epl/utils/launcher.py
epl/utils/metric.py
epl/utils/shape_inference.py
epl/utils/summary_info.py
epl/utils/version.py
pyepl-0.3.0.dist-info/LICENSE
pyepl-0.3.0.dist-info/METADATA
pyepl-0.3.0.dist-info/NOTICE
pyepl-0.3.0.dist-info/WHEEL
pyepl-0.3.0.dist-info/entry_points.txt
pyepl-0.3.0.dist-info/top_level.txt
pyepl-0.3.0.dist-info/RECORD
