Metadata-Version: 2.1
Name: pyepl
Version: 0.3.0
Summary: Easy Parallel Library(EPL) powered by Alibaba.
Home-page: https://easyparallellibrary.readthedocs.io/en/latest/
Author: Alibaba Inc.
License: Apache 2.0
Keywords: distributed training,machine learning,tensorflow
Platform: UNKNOWN
Classifier: License :: OSI Approved :: Apache Software License
Classifier: Programming Language :: Python :: 2.7
Classifier: Programming Language :: Python :: 3.6
Classifier: Programming Language :: Python :: 3.8
Classifier: Operating System :: POSIX :: Linux
Classifier: Topic :: Scientific/Engineering :: Artificial Intelligence
Classifier: Operating System :: OS Independent
License-File: LICENSE
License-File: NOTICE
Requires-Dist: pandas (==0.24.2) ; python_version == "2.7"
Requires-Dist: matplotlib (==2.0.0) ; python_version == "2.7"
Requires-Dist: pandas (==1.1.5) ; python_version >= "3.4"
Requires-Dist: matplotlib (==3.3.4) ; python_version >= "3.4"
Requires-Dist: toposort ; python_version >= "3.4"
